{
  "id": "earth-calendar",
  "title": "Earth Calendar",
  "description": "",
  "version": "0.1.1",
  "authors": [
    {
      "name": "Reyzor",
      "url": "https://www.patreon.com/Reyzor1991",
      "discord": "reyzor1991"
    }
  ],
  "languages": [
    {
      "lang": "en",
      "name": "English",
      "path": "lang/en.json"
    }
  ],
  "esmodules": [
    "earth-calendar.mjs"
  ],
  "styles": [
    "styles/earth-calendar.css"
  ],
  "packFolders": [],
  "packs": [],
  "compatibility": {
    "minimum": "14.360",
    "verified": "14.360",
    "maximum": "14.999"
  },
  "url": "https://github.com/reyzor1991/pf2e-wiki/wiki/Earth-Calendar",
  "manifest": "https://www.dropbox.com/scl/fi/9b5t82eiauqvbjtyyry71/module.json?rlkey=050t3destopdu4p6f5womh98f&st=n9k8ll8i&dl=1",
  "download": "https://www.dropbox.com/scl/fi/4jl22jh1fg2d3xkhd3tno/earth-calendar.zip?rlkey=wsuuf06vqeefq6pymzpu0ztdz&st=4co0drtu&dl=1",
  "relationships": {}
}
